orcapy/BioFile.py
orcapy/CurveProcessing.py
orcapy/ORCA.py
orcapy/Peak.py
orcapy/Plotter.py
orcapy/__init__.py
orcapy-1.0.1.dist-info/LICENSE
orcapy-1.0.1.dist-info/METADATA
orcapy-1.0.1.dist-info/WHEEL
orcapy-1.0.1.dist-info/top_level.txt
orcapy-1.0.1.dist-info/RECORD
