Metadata-Version: 2.1
Name: orcapy
Version: 1.0.1
Summary: Tool for predicting the origin of replication on circular bacterial chromosomes
Home-page: https://github.com/ZoyavanMeel/ORCA
Author: Zoya van Meel
Author-email: zoyavanmeel@gmail.com
License: GPL-3.0
Classifier: License :: OSI Approved :: GNU General Public License v3 (GPLv3)
Classifier: Programming Language :: Python :: 3.11
Classifier: Operating System :: OS Independent
Requires-Python: >=3.9
License-File: LICENSE
Requires-Dist: numpy (>=1.22.3)
Requires-Dist: scikit-learn (>=1.4.0)
Requires-Dist: biopython (>=1.79)
Requires-Dist: scipy (>=1.8.0)
Requires-Dist: matplotlib (>=3.5.2)
Provides-Extra: dev
Requires-Dist: twine (>=5.0.0) ; extra == 'dev'
